int2word/__init__.py
int2word/main.py
int2word-0.2.dist-info/METADATA
int2word-0.2.dist-info/WHEEL
int2word-0.2.dist-info/top_level.txt
int2word-0.2.dist-info/RECORD
