Metadata-Version: 2.1
Name: int2word
Version: 0.2
